<?xml version="1.0" encoding="utf-8" ?>
<?xml-model href="../../Organization/knxprod-support/knx_project_14/knx-editor.xsd" type="application/xml" schematypens="http://www.w3.org/2001/XMLSchema"?>
<KNX xmlns="http://knx.org/xml/project/14" xmlns:op="http://github.com/OpenKNX/OpenKNXproducer">
  <ManufacturerData>
    <Manufacturer RefId="M-00FA">
      <ApplicationPrograms>
        <ApplicationProgram Id="%AID%" ApplicationNumber="203" ApplicationVersion="10" ProgramType="ApplicationProgram" MaskVersion="MV-07B0" Name="WP-Logic" LoadProcedureStyle="MergedProcedure" PeiType="0" DefaultLanguage="de" DynamicTableManagement="false" Linkable="true" MinEtsVersion="4.0">
          <Static></Static>
          <Dynamic>
             <ChannelIndependentBlock>
              <!-- A tab page with general settings -->
              <ParameterBlock Id="AID%_PB-2" Name="General" Text="Allgemeine Einstellungen">
                <!-- <ParameterSeparator Id="%AID%_PS-4" Text="" UIHint="HorizontalRuler" /> -->
                <ParameterSeparator Id="%AID%_PS-nnn" Text="Bridge" UIHint="Headline" />
                <ParameterRefRef RefId="%AID%_P-%T%000001_R-%T%00000101" /> <!-- Bridge Name -->
                <ParameterRefRef RefId="%AID%_P-%T%000002_R-%T%00000201" /> <!-- Modus -->
                <ParameterSeparator Id="%AID%_PS-nnn" Text="" UIHint="HorizontalRuler" />
                <ParameterSeparator Id="%AID%_PS-nnn" Text="WIFI" UIHint="Headline" />
                <ParameterRefRef RefId="%AID%_P-%T%000003_R-%T%00000301" /> <!-- SSID -->
                <ParameterRefRef RefId="%AID%_P-%T%000004_R-%T%00000401" /> <!-- Password -->
                <choose ParamRefId="%AID%_P-%T%000002_R-%T%00000201" >  <!-- Modus -->
                  <when test="1 3"> <!-- Homekit OR Homekit & Hue -->
                    <ParameterSeparator Id="%AID%_PS-nnn" Text="" UIHint="HorizontalRuler" />
                    <ParameterSeparator Id="%AID%_PS-nnn" Text="Homekit" UIHint="Headline" />
                    <ParameterRefRef RefId="%AID%_P-%T%000005_R-%T%00000501" /> <!-- Pairing Code -->
                    <ParameterSeparator Id="%AID%_PS-nnn" Text="Hinweis: Apple lässt beim Koppeln einfache Codes (z.B. nur Einser) nicht zu. Das kann durch ETS nicht geprüft werden. Es wird daher empfohlen den Standard-Wert 46637726 zu verwenden." UIHint="Information" />
                  </when>
                </choose> 
                <ParameterSeparator Id="%AID%_PS-nnn" Text="" UIHint="HorizontalRuler" />

                <ComObjectRefRef RefId="%AID%_O-%T%000001_R-%T%00000101" />     
                 <choose ParamRefId="%AID%_P-%T%000002_R-%T%00000201" >  <!-- Modus -->
                  <when test="1 3"> <!-- Homekit OR Homekit & Hue -->
                    <ComObjectRefRef RefId="%AID%_O-%T%000002_R-%T%00000201" />
                  </when>
                </choose> 
                
              </ParameterBlock>
            </ChannelIndependentBlock>
          </Dynamic>
        </ApplicationProgram>
      </ApplicationPrograms>
    </Manufacturer>
  </ManufacturerData>
</KNX>